listentoeverything/__init__.py
listentoeverything/cli.py
listentoeverything/listen.py
listentoeverything/listentoeverything.py
listentoeverything-0.3.3.dist-info/AUTHORS.rst
listentoeverything-0.3.3.dist-info/LICENSE
listentoeverything-0.3.3.dist-info/METADATA
listentoeverything-0.3.3.dist-info/WHEEL
listentoeverything-0.3.3.dist-info/entry_points.txt
listentoeverything-0.3.3.dist-info/top_level.txt
listentoeverything-0.3.3.dist-info/RECORD
