Metadata-Version: 2.1
Name: listentoeverything
Version: 0.3.3
Summary: Scrapes good music off Reddit, makes a spotify playlist
Home-page: https://github.com/happykhan/listentoeverything
Author: Nabil-Fareed Alikhan
Author-email: nabil@happykhan.com
License: GNU General Public License v3
Keywords: listentoeverything
Platform: UNKNOWN
Classifier: Development Status :: 2 - Pre-Alpha
Classifier: Intended Audience :: Developers
Classifier: License :: OSI Approved :: GNU General Public License v3 (GPLv3)
Classifier: Natural Language :: English
Classifier: Programming Language :: Python :: 3
Classifier: Programming Language :: Python :: 3.5
Classifier: Programming Language :: Python :: 3.6
Classifier: Programming Language :: Python :: 3.7
Requires-Dist: praw (==6.1.1)
Requires-Dist: PyYAML (==5.1)
Requires-Dist: spotipy (==2.4.4)
Requires-Dist: Click (>=6.0)
